{
  "title": "Oh, VisBug! — Make any webpage feel like an artboard 🎨",
  "url": "https://codeburst.io/oh-visbug-make-any-webpage-feel-like-an-artboard-bdb10307c70e",
  "excerpt": "Google is always at the frontiers of creating daring and life-changing developers tools, thanks to Chrome Developers, a really neat tool was introduced at Chrome Developers summit last year’s day 1 Keynote session (14th of November precisely). They call it: Project Visbug.",
  "publication": "Codeburst",
  "date": "January 23, 2019"
}
