{
  "upcoming": [],
  "sessions": [
    {
      "title": "Async iterators in JavaScript and Node.js",
      "teacher": "Luciano Mammino",
      "teacherUrl": "https://twitter.com/loige",
      "date": "May 14, 2021",
      "poster": "/tkyt/async-iterators.png",
      "url": "https://youtu.be/l2CA9FtW1Pw"
    },
    {
      "title": "Building CLI apps with Dart",
      "teacher": "Brett Sutton",
      "teacherUrl": "https://www.linkedin.com/in/brettsutton/",
      "date": "July 2, 2021",
      "poster": "/tkyt/building-cli-apps-with-dart.png",
      "url": "https://youtu.be/yvu7f3lv9AQ"
    },
    {
      "title": "Getting started with RapidAPI",
      "teacher": "Pratham Kumar",
      "teacherUrl": "https://twitter.com/Prathkum",
      "date": "April 20, 2022",
      "poster": "/tkyt/getting-started-with-rapid-api.png",
      "url": "https://youtu.be/QAOkWwrPqZU"
    },
    {
      "title": "Node.js streams",
      "teacher": "Luciano Mammino",
      "teacherUrl": "https://twitter.com/loige",
      "date": "April 29, 2022",
      "poster": "/tkyt/node-js-streams.png",
      "url": "https://youtu.be/ldcfYB_mo6Q"
    },
    {
      "title": "Building APIs with AdonisJS",
      "teacher": "Harminder Virk",
      "teacherUrl": "https://twitter.com/AmanVirk1",
      "date": "May 4, 2022",
      "poster": "/tkyt/building-apis-with-adonis.png",
      "url": "https://youtu.be/_MSQY3lqhCo"
    },
    {
      "title": "Building a landing page with Charkra UI",
      "teacher": "Esther Agbaje",
      "teacherUrl": "https://twitter.com/_estheragbaje",
      "date": "May 23, 2022",
      "poster": "/tkyt/chakra-ui.png",
      "url": "https://youtu.be/0pgnR3p4o2w"
    },
    {
      "title": "Building desktop apps with Electron",
      "teacher": "Praneet Rohida",
      "teacherUrl": "https://twitter.com/praneet_ro",
      "date": "May 26, 2022",
      "poster": "/tkyt/building-desktop-apps-with-electron.png",
      "url": "https://youtu.be/TBvZ4CoCfnM"
    },
    {
      "title": "Zagjs: UI components on state machines",
      "teacher": "Segun Adebayo",
      "teacherUrl": "https://twitter.com/thesegunadebayo",
      "date": "June 29, 2022",
      "poster": "/tkyt/zagjs.png",
      "url": "https://youtu.be/VZHBa5Kgets"
    },
    {
      "title": "Learning TypeScript from scratch",
      "teacher": "Matt Pocock",
      "teacherUrl": "https://twitter.com/mattpocockuk",
      "date": "July 19, 2022",
      "poster": "/tkyt/learn-typescript.png",
      "url": "https://youtu.be/qcFmCKQDa2s"
    },
    {
      "title": "Monorepos, Nx and Lerna",
      "teacher": "Juri Strumpflohner",
      "teacherUrl": "https://twitter.com/juristr",
      "date": "27 September, 2022",
      "poster": "/tkyt/monorepos.png",
      "url": "https://youtu.be/P5Un_z0hH90"
    },
    {
      "title": "Learning Svelte from scratch",
      "teacher": "Geoff Rich",
      "teacherUrl": "https://twitter.com/geoffrich_",
      "date": "29 September, 2022",
      "poster": "/tkyt/learn-svelte.png",
      "url": "https://youtu.be/QoR0AZ-Rov8"
    },
    {
      "title": "Lit and Web Components",
      "teacher": "Elliott Marquez",
      "teacherUrl": "https://twitter.com/techytacos",
      "date": "September 30, 2022",
      "poster": "/tkyt/lit-and-web-components.png",
      "url": "https://youtu.be/j9rn2180mNI"
    },
    {
      "title": "Mutation testing with StrykerJS",
      "teacher": "Nico Jansen",
      "teacherUrl": "https://twitter.com/_nicojs",
      "date": "October 3, 2022",
      "poster": "/tkyt/mutation-testing.png",
      "url": "https://youtu.be/3FN1r43yJHU"
    },
    {
      "title": "Reactivity and SolidJS",
      "teacher": "Ryan Carniato",
      "teacherUrl": "https://twitter.com/RyanCarniato",
      "date": "October 13, 2022",
      "poster": "/tkyt/reactivity-and-solid.png",
      "url": "https://youtu.be/N-Y32BqhoYQ"
    },
    {
      "title": "Eleventy: the underdog site generator",
      "teacher": "Zach Leatherman",
      "teacherUrl": "https://twitter.com/zachleat",
      "date": "October 13, 2022",
      "poster": "/tkyt/eleventy-with-zach.png",
      "url": "https://youtu.be/ayOouJv6WYg"
    },
    {
      "title": "Why the world needs Qwik",
      "teacher": "Miško Hevery",
      "teacherUrl": "https://twitter.com/mhevery",
      "date": "October 17, 2022",
      "poster": "/tkyt/why-qwik.png",
      "url": "https://youtu.be/IRw9efkn9UA"
    },
    {
      "title": "Building resumable websites with Qwik",
      "teacher": "Manu Almeida",
      "teacherUrl": "https://twitter.com/manucorporat",
      "date": "October 18, 2022",
      "poster": "/tkyt/manu-resumability.png",
      "url": "https://youtu.be/umASDvjaKTY"
    },
    {
      "title": "Styling with Design Tokens and Token CSS",
      "teacher": "Nate Moore",
      "teacherUrl": "https://twitter.com/n_moore",
      "date": "October 20, 2022",
      "poster": "/tkyt/design-tokens.png",
      "url": "https://youtu.be/3M1oHN2ydwA"
    },
    {
      "title": "Building full-stack Next.js apps",
      "teacher": "Brandon Bayer",
      "teacherUrl": "https://twitter.com/flybayer",
      "date": "November 2, 2022",
      "poster": "/tkyt/nextjs-brandon.png",
      "url": "https://youtu.be/XI8sztoNsJQ"
    },
    {
      "title": "Serverless from scratch",
      "teacher": "Jason Lengstorf",
      "teacherUrl": "https://twitter.com/jlengstorf",
      "date": "November 16, 2022",
      "poster": "/tkyt/serverless-from-scratch.png",
      "url": "https://youtu.be/a_OVJvT7z6A"
    },
    {
      "title": "Getting started with Platformatic DB",
      "teacher": "Matteo Collina",
      "teacherUrl": "https://twitter.com/matteocollina",
      "date": "November 24, 2022",
      "poster": "/tkyt/platformatic-db.png",
      "url": "https://youtu.be/iDgE0OVeBWo"
    },
    {
      "title": "Building hybrid web apps with Nuxt",
      "teacher": "Daniel Roe",
      "teacherUrl": "https://twitter.com/danielcroe",
      "date": "November 28, 2022",
      "poster": "/tkyt/hybrid-apps-with-nuxt.png",
      "url": "https://youtu.be/OXcFuEyngqA"
    },
    {
      "title": "Learning modern Angular",
      "teacher": "Chau Tran",
      "teacherUrl": "https://twitter.com/Nartc1410",
      "date": "December 2, 2022",
      "poster": "/tkyt/modern-angular.png",
      "url": "https://youtu.be/J6s6bb3XEEI"
    },
    {
      "title": "Embracing the strengths of the web with Marko",
      "teacher": "Dylan Piercey",
      "teacherUrl": "https://twitter.com/dylan_piercey",
      "date": "January 10, 2023",
      "poster": "/tkyt/marko.png",
      "url": "https://youtu.be/MWUZK_mbdlU"
    },
    {
      "title": "Getting started with Wundergraph",
      "teacher": "Jens Neuse",
      "teacherUrl": "https://twitter.com/jensneuse_de",
      "date": "January 11, 2023",
      "poster": "/tkyt/wundergraph.png",
      "url": "https://youtu.be/s9By-LXnxcI"
    },
    {
      "title": "magic-regexp: the readable RegExp alternative",
      "teacher": "Daniel Roe",
      "teacherUrl": "https://twitter.com/danielcroe",
      "date": "January 16, 2023",
      "poster": "/tkyt/magic-regular-expressions.png",
      "url": "https://youtu.be/tgRMf0_Bgdo"
    },
    {
      "title": "Getting started with 3D modelling in React",
      "teacher": "Sara Vieira",
      "teacherUrl": "https://twitter.com/NikkitaFTW",
      "date": "January 16, 2023",
      "poster": "/tkyt/3d-react.png",
      "url": "https://youtu.be/-JmgG7Vtpbo"
    },
    {
      "title": "Building a blog with BlogHunch",
      "teacher": "Subham Mitra",
      "teacherUrl": "https://twitter.com/icodefuture",
      "date": "January 18, 2023",
      "poster": "/tkyt/bloghunch.png",
      "url": "https://youtu.be/jxg2FiAHBok"
    },
    {
      "title": "Getting started with Formidable",
      "teacher": "Donald Pakkies",
      "teacherUrl": "https://twitter.com/DonaldPakkies",
      "date": "January 18, 2023",
      "poster": "/tkyt/formidable.png",
      "url": "https://youtu.be/3PeX6fbGrN8"
    },
    {
      "title": "Why attention to detail matters",
      "teacher": "Sanjin Celeski",
      "teacherUrl": "https://twitter.com/sanjinceleski",
      "date": "February 3, 2023",
      "poster": "/tkyt/sanjin.png",
      "url": "https://youtu.be/7JacYoUm6lk"
    },
    {
      "title": "Building a Qwik app",
      "teacher": "Yoav Ganbar",
      "teacherUrl": "https://twitter.com/HamatoYogi",
      "date": "February 6, 2023",
      "poster": "/tkyt/build-a-qwik-app.png",
      "url": "https://youtu.be/qqbi9WBe-ts"
    },
    {
      "title": "Getting started with tRPC",
      "teacher": "Anthony Shew",
      "teacherUrl": "https://twitter.com/anthonysheww",
      "date": "February 24, 2023",
      "poster": "/tkyt/trpc.png",
      "url": "https://youtu.be/yMcdJMAIsec"
    },
    {
      "title": "Decoding the Fastify plugin system",
      "teacher": "Manuel Spigolon",
      "teacherUrl": "https://twitter.com/ManuEomm",
      "date": "April 3, 2023",
      "poster": "/tkyt/manuel.png",
      "url": "https://youtu.be/BnnL7fAKqNU"
    },
    {
      "title": "Building an API with Nest",
      "teacher": "Jay Cooper Bell",
      "teacherUrl": "https://twitter.com/JayCooperBell",
      "date": "April 4, 2023",
      "poster": "/tkyt/jay.png",
      "url": "https://youtu.be/nGPe0hgEnCQ"
    },
    {
      "title": "Getting started with Redwood",
      "teacher": "Anthony Campolo",
      "teacherUrl": "https://twitter.com/ajcwebdev",
      "date": "April 5, 2023",
      "poster": "/tkyt/anthony.png",
      "url": "https://youtu.be/Ih6cWaII1mc"
    },
    {
      "title": "Building full-stack apps with AWS Amplify",
      "teacher": "Erik Hanchett",
      "teacherUrl": "https://twitter.com/ErikCH",
      "date": "April 6, 2023",
      "poster": "/tkyt/aws-amplify.png",
      "url": "https://youtu.be/kq0uQOW67qs"
    },
    {
      "title": "WTF is UnoCSS?",
      "teacher": "Anthony Fu",
      "teacherUrl": "https://twitter.com/antfu7",
      "date": "April 10, 2023",
      "poster": "/tkyt/anthony-fu.png",
      "url": "https://youtu.be/nHag_UhwORY"
    }
  ]
}
